MANIFEST.in
README.md
setup.py
bin/pysftpjail
bin/pysftpproxy
examples/mongodb_gridfs/README.md
examples/mongodb_gridfs/mongostorage.py
examples/mongodb_gridfs/pysftpmongo
examples/mongodb_gridfs/test_server_mongo.py
pysftpserver/__init__.py
pysftpserver/abstractstorage.py
pysftpserver/futimes.py
pysftpserver/proxystorage.py
pysftpserver/pysftpexceptions.py
pysftpserver/server.py
pysftpserver/stat_helpers.py
pysftpserver/storage.py
pysftpserver/virtualchroot.py
pysftpserver.egg-info/PKG-INFO
pysftpserver.egg-info/SOURCES.txt
pysftpserver.egg-info/dependency_links.txt
pysftpserver.egg-info/not-zip-safe
pysftpserver.egg-info/requires.txt
pysftpserver.egg-info/top_level.txt