Metadata-Version: 1.1
Name: pysftpserver
Version: 1.4.0
Summary: An OpenSSH SFTP wrapper in Python.
Home-page: https://github.com/unbit/pysftpserver
Author: Unbit
Author-email: info@unbit.com
License: MIT
Keywords: pysftpserver,sftp,openssh,ssh,jail
Platform: UNKNOWN
Classifier: Programming Language :: Python
Classifier: Programming Language :: Python :: 3
Classifier: Development Status :: 6 - Mature
Classifier: Environment :: Other Environment
Classifier: Intended Audience :: Developers
Classifier: Intended Audience :: End Users/Desktop
Classifier: Intended Audience :: Information Technology
Classifier: License :: OSI Approved :: MIT License
Classifier: Operating System :: OS Independent
Classifier: Topic :: System :: Shells
Classifier: Topic :: System :: System Shells
Classifier: Topic :: Internet :: File Transfer Protocol (FTP)
Classifier: Topic :: Utilities
